sonotools/__init__.py
sonotools/__version__.py
sonotools-0.1.8.dist-info/LICENSE.txt
sonotools-0.1.8.dist-info/METADATA
sonotools-0.1.8.dist-info/WHEEL
sonotools-0.1.8.dist-info/top_level.txt
sonotools-0.1.8.dist-info/RECORD
